{
  "schema_version": "1.0",
  "id": "kv.mechanics.checks.who_rolls",
  "type": "rule_card",
  "title": "Кто выполняет проверку",
  "source": {
    "book": "kv_core",
    "edition": "02_03_2026_с_рубрикатором",
    "section": "Выполнение действий → Выполнение проверок → Кто выполняет проверку",
    "pages": [
      17
    ]
  },
  "verified": false,
  "locale": "ru",
  "terminology": "pandora_box",
  "notes": "",
  "payload": {
    "subsystem": "checks",
    "title": "Кто выполняет проверку",
    "source_text": [
      "Если проверка вызвана действиями героя игрока, кости бросает тот, кто им управляет. Но когда проверка — это реакция на что-то, описанное хранителем, выбор не так очевиден. Вообще лучше, чтобы проверку выполнял кто-то один из игроков, кроме случаев, когда нечто касается всех героев отряда. Для проверки игроки выбирают героя, лучше подходящего для задачи, и затем могут воспользоваться правилами помощи («Помощь», стр. 20)."
    ],
    "summary": "Кости бросает игрок действующего героя; при реакции на события хранителя проверку выполняет один игрок за лучше всего подходящего героя, кроме случаев, касающихся всего отряда.",
    "parameters": {},
    "related": [
      "kv.mechanics.checks.assistance"
    ]
  }
}
