{
  "schema_version": "1.0",
  "id": "kv.mechanics.solo.srazhayas_s_soboy",
  "type": "rule_card",
  "title": "Сражаясь с собой",
  "source": {
    "book": "igra_dlya_odnogo",
    "edition": "на_рассылку_03_04_2026",
    "section": "сражение",
    "pages": [
      18
    ]
  },
  "verified": false,
  "locale": "ru",
  "terminology": "pandora_box",
  "notes": "",
  "payload": {
    "subsystem": "solo",
    "title": "Сражаясь с собой",
    "source_text": [
      "Управление врагами в роли хранителя против собственного героя порой кажется наигранным и вынужденным, но помните: цель сражения не «выиграть», а создать впечатляющий, интересный или важный бой, добавляющий глубины сюжету и испытывающий героя, чем бы бой ни закончился. Если сомневаетесь, как всё обыграть, следуйте «принципу крутизны». Делайте происходящее увлекательным и динамичным. Устраивайте интересные сражения, опираясь на любимые эпические баталии и зрелищные сцены из фильмов и литературы. А таблица ответов и таблица преданий вам в этом помогут."
    ],
    "summary": "Совет по вождению боя за себя: цель не «выиграть», а сделать бой впечатляющим и значимым для сюжета; при сомнении — «принцип крутизны»; таблицы ответов и преданий помогают.",
    "parameters": {
      "oracle_refs": [
        "kv.solo.answers",
        "kv.solo.lore"
      ]
    },
    "related": [
      "kv.mechanics.combat.boy"
    ]
  }
}
